{
  "video_id": "yt_gA0nwBndJ6w",
  "title": "Robinhood CEO Vlad Tenev on Org Structure",
  "summary": "视频探讨了Robinhood CEO Vlad Tenev关于组织结构中高层领导者与基层员工之间痛苦分担的原则，强调快速发布产品的重要性。",
  "key_points": [
    {
      "timestamp": 0,
      "title": "痛苦分担原则",
      "content": "员工希望管理者经历比他们更多的痛苦。"
    },
    {
      "timestamp": 60,
      "title": "痛苦分担程度",
      "content": "高层领导者承担5天，管理者4天，个人贡献者3天的痛苦。"
    },
    {
      "timestamp": 120,
      "title": "快速发布原则",
      "content": "快速发布产品需要从高层开始，并愿意为他人要求做到更多。"
    },
    {
      "timestamp": 180,
      "title": "高层责任",
      "content": "快速发布需要高层领导者带头。"
    },
    {
      "timestamp": 240,
      "title": "自我要求",
      "content": "领导者应愿意为团队要求做到更高标准。"
    }
  ],
  "tags": [
    "组织结构",
    "痛苦分担",
    "快速发布",
    "领导力",
    "Robinhood"
  ],
  "generated_at": "2025-12-21T02:32:49.408422Z"
}