{
  "video_id": "yt_OUJznQbHkI4",
  "title": "Founder Stories: Rishi Choudhary",
  "summary": "Rishi Choudhary分享了他作为Castle AI创始人的经历，从在YC创业前在常规工作中对企业的期望，到创立Castle AI为大型银行和抵押贷款机构提供语音AI代理，以及他与客户合作帮助塑造AI未来规划。",
  "key_points": [
    {
      "timestamp": 0,
      "title": "自我介绍",
      "content": "Rishi Choudhary介绍自己是Castle AI的创始人和CEO。"
    },
    {
      "timestamp": 5,
      "title": "业务描述",
      "content": "Castle AI为大型银行和抵押贷款机构开发语音AI代理以自动化电话。"
    },
    {
      "timestamp": 9,
      "title": "业务成果",
      "content": "公司业务进展良好，与国家排名前25的金融服务商合作。"
    },
    {
      "timestamp": 17,
      "title": "个人生活变化",
      "content": "Rishi的生活因创业而完全改变。"
    },
    {
      "timestamp": 22,
      "title": "创业前经历",
      "content": "在加入YC之前，Rishi在一家公司从事常规工作，对企业的期望很高。"
    },
    {
      "timestamp": 25,
      "title": "企业工作感受",
      "content": "Rishi认为在大型企业中很难推动创新和新产品的开发。"
    },
    {
      "timestamp": 36,
      "title": "当前工作内容",
      "content": "现在Rishi可以直接与大型银行的执行团队合作，帮助他们制定AI发展路线图。"
    }
  ],
  "tags": [
    "创业故事",
    "人工智能",
    "金融科技",
    "语音AI",
    "企业转型"
  ],
  "generated_at": "2025-12-21T02:39:57.765900Z"
}